{"val": {"log_prob_true": -3.610278606414795, "time_log_prob": 2.1511709690093994, "loss": 3.6113176345825195, "log_prob": -3.6113176345825195}, "epoch": 999, "_timestamp": 1715683934.06562, "train": {"loss": 4.026026725769043, "log_prob": -4.02520227432251, "time_forward": 1.4150559902191162, "lr": 0.00023782688525533205}, "_runtime": 5779.335546970367, "_step": 999, "x_obs": {"_type": "image-file", "sha256": "bf8e318dc21215260f381b7621632103c72fca0999cda06b19fa9b8f5b51a1d5", "size": 369731, "path": "media/images/x_obs_999_bf8e318dc21215260f38.png", "format": "png", "width": 994, "height": 986}, "x_int_1=25p": {"_type": "image-file", "sha256": "3c40e03d503d19ca642ec4910773b763ca0cb879034b5307adad2635c23e8d2d", "size": 448765, "path": "media/images/x_int_1=25p_999_3c40e03d503d19ca642e.png", "format": "png", "width": 994, "height": 986}, "x_int_1=50p": {"_type": "image-file", "sha256": "636874ff1717f751d3d1f95947ad17e5576472f4e98dd9d4c98471cbaf412b47", "size": 455728, "path": "media/images/x_int_1=50p_999_636874ff1717f751d3d1.png", "format": "png", "width": 994, "height": 986}, "x_int_1=75p": {"_type": "image-file", "sha256": "c6946b9332b829fc765f66f04c8365467c39d9bb8017805f917afc56ba3672e0", "size": 470352, "path": "media/images/x_int_1=75p_999_c6946b9332b829fc765f.png", "format": "png", "width": 994, "height": 986}, "x_int_2=25p": {"_type": "image-file", "sha256": "369d62d205c7b65b86b797664c79299cd8769d4890475447d1f7a523b8b82e73", "size": 444180, "path": "media/images/x_int_2=25p_999_369d62d205c7b65b86b7.png", "format": "png", "width": 994, "height": 986}, "x_int_2=50p": {"_type": "image-file", "sha256": "53d34a89bd12c17367f856e5e17fd1fde5e51d3f90bd0226ba4bc84828f18a13", "size": 420820, "path": "media/images/x_int_2=50p_999_53d34a89bd12c17367f8.png", "format": "png", "width": 994, "height": 986}, "x_int_2=75p": {"_type": "image-file", "sha256": "5ee01ea03de2347c19b2b24b8e9c9aa38bf9a68f1e621c7c5058a1e47089a9fa", "size": 418859, "path": "media/images/x_int_2=75p_999_5ee01ea03de2347c19b2.png", "format": "png", "width": 994, "height": 986}, "x_int_3=25p": {"_type": "image-file", "sha256": "e8383b678cf2d1397c4eef1df22d20308e5f944fc5ce74a281057c67335b03b3", "size": 422390, "path": "media/images/x_int_3=25p_999_e8383b678cf2d1397c4e.png", "format": "png", "width": 994, "height": 986}, "x_int_3=50p": {"_type": "image-file", "sha256": "352a97529dba367a13da22d20f267aff7511dc5b5ce7183baeaafa3504732fbc", "size": 394752, "path": "media/images/x_int_3=50p_999_352a97529dba367a13da.png", "format": "png", "width": 994, "height": 986}, "x_int_3=75p": {"_type": "image-file", "sha256": "2c20abb83b0a6c46074ab00f0ffb530f3cc27db4e13460c496ba265a2098292f", "size": 409720, "path": "media/images/x_int_3=75p_999_2c20abb83b0a6c46074a.png", "format": "png", "width": 994, "height": 986}, "_wandb": {"runtime": 5778}}